glamconv/__init__.py
glamconv/utils.py
glamconv/cli/__init__.py
glamconv/cli/commands.py
glamconv/eac/__init__.py
glamconv/eac/adjusters.py
glamconv/eac/cleaners.py
glamconv/eac/default-eac-cpf-to-ape-settings.json
glamconv/eac/formats.py
glamconv/eac/namespacers.py
glamconv/eac/registration.py
glamconv/eac/required_elts_adders.py
glamconv/eac/supplementers.py
glamconv/eac/text_data.py
glamconv/eac/utils.py
glamconv/eac/validators.py
glamconv/eac/ape-eac-schema/apeEAC-CPF.xsd
glamconv/eac/ape-eac-schema/xlink.xsd
glamconv/eac/ape-eac-schema/xml.xsd
glamconv/eac/eac-cpf-schema/cpf.xsd
glamconv/eac/eac-cpf-schema/xlink.xsd
glamconv/eac/eac-cpf-schema/xml.xsd
glamconv/ead/__init__.py
glamconv/ead/adjusters.py
glamconv/ead/arch_data.py
glamconv/ead/cleaners.py
glamconv/ead/default-ead2-to-ape-settings.json
glamconv/ead/ead_2002_correcters.py
glamconv/ead/formats.py
glamconv/ead/header.py
glamconv/ead/link_managers.py
glamconv/ead/namespacers.py
glamconv/ead/registration.py
glamconv/ead/supplementers.py
glamconv/ead/text_data.py
glamconv/ead/utils.py
glamconv/ead/validators.py
glamconv/ead/ape-ead-schema/apeEAD.xsd
glamconv/ead/ape-ead-schema/xlink.xsd
glamconv/ead/ead-2002-dtd/ead.dtd
glamconv/ead/ead-2002-dtd/eadlocal.ent
glamconv/ead/ead-2002-dtd/iso-cyr1.ent
glamconv/ead/ead-2002-dtd/iso-cyr2.ent
glamconv/ead/ead-2002-dtd/iso-dia.ent
glamconv/ead/ead-2002-dtd/iso-grk1.ent
glamconv/ead/ead-2002-dtd/iso-grk2.ent
glamconv/ead/ead-2002-dtd/iso-grk3.ent
glamconv/ead/ead-2002-dtd/iso-grk4.ent
glamconv/ead/ead-2002-dtd/iso-lat1.ent
glamconv/ead/ead-2002-dtd/iso-lat2.ent
glamconv/ead/ead-2002-dtd/iso-num.ent
glamconv/ead/ead-2002-dtd/iso-pub.ent
glamconv/ead/ead-2002-dtd/iso-tech.ent
glamconv/transformer/__init__.py
glamconv/transformer/actions.py
glamconv/transformer/formats.py
glamconv/transformer/libraries.py
glamconv/transformer/logger.py
glamconv/transformer/parameters.py
glamconv/transformer/processes.py
glamconv/transformer/rw_actions.py
glamconv-0.3.1.dist-info/METADATA
glamconv-0.3.1.dist-info/WHEEL
glamconv-0.3.1.dist-info/top_level.txt
glamconv-0.3.1.dist-info/RECORD
