Metadata-Version: 2.1
Name: glamconv
Version: 0.3.1
Summary: set of tools to import, transform and manipulate standard GLAM formats (EAD,
Home-page: http://www.logilab.org/project/glamconv
Author: Logilab S.A. (Paris, FRANCE)
Author-email: contact@logilab.fr
License: LGPL
Classifier: Programming Language :: Python
Requires-Dist: lxml
